main.py
quackstack-0.0.1.dist-info/METADATA
quackstack-0.0.1.dist-info/WHEEL
quackstack-0.0.1.dist-info/top_level.txt
quackstack-0.0.1.dist-info/RECORD
