Metadata-Version: 2.4
Name: quackstack
Version: 0.0.1
Summary: A high-performance, medallion-architecture framework for data lakes and scraping.
Author-email: Alexandria Hawthorne <alexandria@politizen.org>
Maintainer-email: Politizen SPC maintainers <maintainers@politizen.org>
Requires-Python: >=3.12
Requires-Dist: fsspec>=2025.12.0
Requires-Dist: ibis-framework[duckdb]>=11.0.0
Requires-Dist: polars>=1.36.1
